vxmessenger/__init__.py
vxmessenger/api.py
vxmessenger/plugins.py
vxmessenger/transport.py
vxmessenger/webhook.py
vxmessenger-2.0.1.dist-info/top_level.txt
vxmessenger-2.0.1.dist-info/METADATA
vxmessenger-2.0.1.dist-info/DESCRIPTION.rst
vxmessenger-2.0.1.dist-info/metadata.json
vxmessenger-2.0.1.dist-info/WHEEL
vxmessenger-2.0.1.dist-info/RECORD
