Metadata-Version: 2.0
Name: vxmessenger
Version: 2.0.1
Summary: This is the vxmessenger project.
Home-page: https://github.com/praekeltfoundation/vumi-messenger
Author: Praekelt Foundation
Author-email: dev@praekeltfoundation.org
License: BSD
Keywords: vxmessenger
Platform: UNKNOWN
Classifier: Intended Audience :: Developers
Classifier: Natural Language :: English
Classifier: Programming Language :: Python :: 2.7
Requires-Dist: Klein
Requires-Dist: click
Requires-Dist: treq
Requires-Dist: vumi
Requires-Dist: junebug
